MANIFEST.in
README.md
pip_readme.md
setup.cfg
setup.py
./.gitignore
./.project
./.pydevproject
./LICENSE
./README.md
./_config.yml
./main_00.py
./pip_readme.md
./requirements.txt
./setup.cfg
./setup.py
./uniform_classification_regression.txt
evaluation_framework/__init__.py
evaluation_framework/__init__.pyc
evaluation_framework/abstract_dataManager.py
evaluation_framework/abstract_dataManager.pyc
evaluation_framework/abstract_evaluationManager.py
evaluation_framework/abstract_evaluationManager.pyc
evaluation_framework/abstract_model.py
evaluation_framework/abstract_model.pyc
evaluation_framework/abstract_taskManager.py
evaluation_framework/abstract_taskManager.pyc
evaluation_framework/evaluationManager.py
evaluation_framework/evaluationManager.pyc
evaluation_framework/hdf5_dataManager.py
evaluation_framework/hdf5_dataManager.pyc
evaluation_framework/manager.py
evaluation_framework/manager.pyc
evaluation_framework/txt_dataManager.py
evaluation_framework/txt_dataManager.pyc
evaluation_framework.egg-info/PKG-INFO
evaluation_framework.egg-info/SOURCES.txt
evaluation_framework.egg-info/dependency_links.txt
evaluation_framework.egg-info/requires.txt
evaluation_framework.egg-info/top_level.txt
evaluation_framework/Classification/__init__.py
evaluation_framework/Classification/classification_model.py
evaluation_framework/Classification/classification_taskManager.py
evaluation_framework/Classification/data/AAUP.tsv
evaluation_framework/Classification/data/Cities.tsv
evaluation_framework/Classification/data/Forbes.tsv
evaluation_framework/Classification/data/MetacriticAlbums.tsv
evaluation_framework/Classification/data/MetacriticMovies.tsv
evaluation_framework/Clustering/__init__.py
evaluation_framework/Clustering/clustering_model.py
evaluation_framework/Clustering/clustering_taskManager.py
evaluation_framework/Clustering/data/cities2000AndCountries_cluster.tsv
evaluation_framework/Clustering/data/citiesAndCountries_cluster.tsv
evaluation_framework/Clustering/data/citiesMoviesAlbumsCompaniesUni_cluster.tsv
evaluation_framework/Clustering/data/teams_cluster.tsv
evaluation_framework/DocumentSimilarity/__init__.py
evaluation_framework/DocumentSimilarity/computeScoreAverage.py
