Metadata-Version: 1.1
Name: evaluation-framework
Version: 1.3
Summary: Evaluation Framework for testing and comparing graph embedding techniques
Home-page: https://github.com/mariaangelapellegrino/Evaluation-Framework
Author: Maria Angela Pellegrino
Author-email: mariaangelapellegrino94@gmail.com
License: apache-2.0
Download-URL: https://github.com/mariaangelapellegrino/Evaluation-Framework/archive/v_1.3.tar.gz
Keywords: evaluation,graph-embedding,python,library,benchmark-framework,machine learning tasks,semantic tasks
Platform: UNKNOWN
Classifier: Development Status :: 3 - Alpha
Classifier: Intended Audience :: Developers
Classifier: Topic :: Software Development :: Build Tools
Classifier: License :: OSI Approved :: Apache Software License
Classifier: Programming Language :: Python :: 2.7
